Workbook
Name НЯХ: 'План счетов'!$A$2:$A$972
Name НЯХ: #REF!

Sheet План счетов
A1: № | B1: Номгўи њисобњо | C1: Рамзи сатр
A2: «1 11 110» | B2: Воситаҳои пулӣ бо асъори миллӣ | C2: 1 | D2: Денежные средства в национальной валюте | E2: касса
A3: «1 11 120» | B3: Воситаҳои пулӣ бо асъори хориҷӣ | C3: 1
A4: «1 11 130» | B4: Чекҳо бо асъори миллӣ | C4: 1
A5: «1 11 140» | B5: Чекҳо бо асъори хориҷӣ | C5: 1
A6: «1 11 141» | B6: Чекҳо бо рубли русӣ | C6: 1
A7: «1 11 142» | B7: Чекҳо бо доллари ИМА | C7: 1
A8: «1 11 143» | B8: Чекҳо бо Евро | C8: 1
A9: «1 11 210» | B9: ҲЯХ-и Буҷети ҷумҳуриявӣ (БҶ) бо асъори миллӣ | C9: 1
A10: «1 11 220» | B10: ҲЯХ-и Буҷети маҳаллӣ (БМ) бо асъори миллӣ | C10: 1
A11: «1 11 231» | B11: ҲЯХ-и ҳисоби махсуси БҶ бо асъори миллӣ – маблағҳои ташкилотҳои буҷетӣ (МТБ) | C11: 1
A12: «1 11 239» | B12: ҲЯХ-и ҳисоби махсуси БҶ бо асъори миллӣ - маблағҳои муайяннашуда (ММН) | C12: 1
A13: «1 11 241» | B13: ҲЯХ-и ҳисоби махсуси БМ бо асъори миллӣ – маблағҳои ташкилотҳои буҷетӣ (МТБ) | C13: 1
A14: «1 11 249» | B14: ҲЯХ-и ҳисоби махсуси БМ бо асъори миллӣ - маблағҳои муайяннашуда (ММН) | C14: 1
... A17: «1 11 253» | B17: ҲЯХ-и ҳисобҳои шахсии маблағҳои буҷетии БҶ ташкилотҳои буҷетӣ бо асъори миллӣ | C17: 1
A18: «1 11 254» | B18: ҲЯХ-и ҳисобҳои шахсии маблағҳои буҷетии БМ ташкилотҳои буҷетӣ бо асъори миллӣ | C18: 1 | D18: ЕКС лицевых счетов бюджетных средств МБ бюджетных организаций в национальной валюте | E18: Банк
A19: «1 11 255» | B19: Њисоби ягонаи хазинадории (ЊЯХ) њисобњои шахсии маблаѓњои буљетии Агентии суѓуртаи иљтимої ва нафаќа (АСИН) бо асъои миллї | C19: 1
A20: «1 11 260» | B20: Ҳисоби маблағҳои ФҲИА бо асъори миллӣ | C20: 1
A21: «1 11 270» | B21: Ҳисоби интиколии БҶ бо асъори миллӣ | C21: 1
A22: «1 11 280» | B22: Маблаѓњо барои нигоњдории дастгоњи марказии АСИН | C22: 1
A23: «1 11 310» | B23: ҲЯХ-и буҷети ҷумҳуриявӣ (БҶ) бо асъори хориҷӣ | C23: 1
A24: «1 11 320» | B24: ҲЯХ-и буҷети маҳаллӣ (БМ) бо асъори хориҷӣ | C24: 1
A25: «1 11 330» | B25: ҲЯХ-и ҳисоби махсуси БҶ бо асъори хориҷӣ | C25: 1
A26: «1 11 340» | B26: ҲЯХ-и ҳисоби махсуси БМ бо асъори хориҷӣ | C26: 1
A27: «1 11 350» | B27: ҲЯХ-и ҳисобҳои шахсии ташкилотҳои буҷетӣ бо асъори хориҷӣ | C27: 1
A28: «1 11 351» | B28: ҲЯХ-и ҳисобҳои шахсии ташкилотҳои буҷетӣ бо асъори хориҷӣ – БҶ | C28: 1
A29: «1 11 352» | B29: ҲЯХ-и ҳисобҳои шахсии ташкилотҳои буҷетӣ бо асъори хориҷӣ – маблағҳои махсуси БҶ | C29: 1
A30: «1 11 353» | B30: ҲЯХ-и ҳисобҳои шахсии ташкилотҳои буҷетӣ бо асъори хориҷӣ – маблағҳои БМ | C30: 1
... A93: «1 14 540» | B93: Ҳақи саҳмҳо барои қабул - асъори хориҷӣ | C93: 2
A94: «1 14 610» | B94: Қарздориҳои дебитории шахсҳои ҳисобдеҳ | C94: 2 | D94: =B94 -> Қарздориҳои дебитории шахсҳои ҳисобдеҳ | E94: 10520
A95: «1 14 620» | B95: Қарздориҳои дебитории ҳайати кормандон марбут ба музди меҳнат ва пардохтҳои дигар | C95: 2
A96: «1 14 630» | B96: Қарздориҳои дебитории марбут ба норасоиҳои ошкоршуда | C96: 2
A97: «1 14 700» | B97: Пардохтҳои иҷоравӣ барои қабул | C97: 2
A98: «1 14 800» | B98: Қисми ҷории қарздории дебитории дарозмуддат | C98: 2
A99: «1 14 900» | B99: Қарздории дебиторӣ аз рӯи дигар амалиётхо | C99: 2
A100: «1 15 100» | B100: Пешпардохтҳои додашуда барои молхо | C100: 4
A101: «1 15 200» | B101: Пешпардохтҳои додашуда барои иљрои кор ва хизматрасониҳо | C101: 4
A102: «1 15 300» | B102: Пешпардохтҳои додашуда барои иҷора | C102: 4
A103: «1 15 400» | B103: Пешпардохтҳо барои андоз | C103: 4
A104: «1 15 510» | B104: Пешпардохтҳои Хазинадорӣ оиди пардохдҳои ҷубронӣ, кўмакпулӣ | C104: 4
A105: «1 15 520» | B105: Пешпардохтҳо барои қарздиҳии шахсҳои воқеъӣ дар доираи барномаҳои иҷтимоӣ аз ҳисоби маблағҳои БҶ. | C105: 4
A106: «1 15 900» | B106: Дигар пешпардохтҳои додашуда | C106: 4
... A312: «1 80 200» | B312: ҲМҚ (СДР) | C312: 8
A313: «2 11 110» | B313: Ҳисобҳо барои пардохт | C313: 13 | D313: Счета к оплате | E313: 22010
A314: «2 11 120» | B314: Пешпардохтҳои гирифташуда | C314: 13 | D314: авансы полученные
A315: «2 11 121» | B315: Воридотҳои пешпардохтӣ аз хадамоти гумрук | C315: 13
A316: «2 11 122» | B316: Рамзҳои нокушодаи пардохтҳои ТАМБ “Амонатбанк” | C316: 13
A317: «2 11 129» | B317: Дигар пешпардохтњои гирифташуда | C317: 13 | D317: Прочие авансы полученные
A318: «2 11 130» | B318: Амонатњои бозгаштшаванда | C318: 13
A319: «2 11 140» | B319: Ҳисобҳо барои пардохт- маблағҳои баргардондашудаи ТБ мутобиқи иттилоотҳои нодуруст нишондодашуда | C319: 13
A320: «2 11 190» | B320: Дигар ҳисобҳо барои пардохт | C320: 13 | D320: прочие счета к оплате
A321: «2 11 210» | B321: Қоғазҳои қиматнок, ба ғайр аз саҳмияҳо | C321: 14
A322: «2 11 211» | B322: Васиқаҳои хазинадорӣ | C322: 14
A323: «2 11 212» | B323: Вомбаргҳои давлатӣ | C323: 14
A324: «2 11 221» | B324: Аз Бонки миллии Ҷумҳурии Тоҷикистон | C324: 14
A325: «2 11 230» | B325: Дигар қарзҳо ва вомҳо | C325: 14
A326: «2 11 240» | B326: Қисми ҷории ӯҳдадориҳои қарзии дарозмуддат | C326: 14
A327: «2 11 250» | B327: Мусоидаҳои (қарзҳои) аз буҷети ҷумҳуриявӣ гирифташуда | C327: 14
A328: «2 11 260» | B328: Мусоидаҳои (қарзҳои) аз буҷети маҳаллӣ гирифташуда | C328: 14
A329: «2 11 300» | B329: Дисконтҳои (тахфифҳо) марбут ба вомбаргҳо ва васиқаҳо | C329: 14
A330: «2 11 400» | B330: Подошҳои (изофанархҳои) марбут ба вомбаргҳо | C330: 14
A331: «2 11 510» | B331: Музди меҳнат барои пардохт | C331: 17 | D331: Зарплата к выплате | E331: ЗП
A332: «2 11 520» | B332: Суди саҳмияҳо барои пардохт | C332: 13
A333: «2 11 530» | B333: Фоизҳо барои пардохт | C333: 13
A334: «2 11 540» | B334: Аъзоҳаққии иттифоқи касаба барои пардохт | C334: 13
A335: «2 11 541» | B335: Аъзоҳаққии иттифоқи касаба барои пардохт - ба иттифоқи касабаи ҷумҳуриявӣ | C335: 13
A336: «2 11 542» | B336: Аъзоҳаққии иттифоқи касаба барои пардохт - ба иттифоқи касабаи муассиса | C336: 13
A337: «2 11 550» | B337: Депонентҳо барои пардохт | C337: 13
A338: «2 11 560» | B338: Идрорпулиҳо барои пардохт | C338: 13
A339: «2 11 570» | B339: Рухсатпулиҳо барои пардохт | C339: 13
A340: «2 11 580» | B340: Уњдадорињои њисобкардашуда ба шахсони њисоботдењ | C340: 13
A341: «2 11 590» | B341: Дигар ӯҳдадориҳои ҳисобкардашуда | C341: 13
A342: «2 11 591» | B342: Ўҳдадориҳо оиди баргардондани андозҳо ба андозсупорандагон | C342: 13
A343: «2 11 599» | B343: Дигар ӯҳдадориҳои ҳисобкардашуда | C343: 13
... A371: «2 11 966» | B371: Уњдадории АСИН аз руи интиќоли маблаѓњои пулї ба ташкилотњои буљетї | C371: 13
A372: «2 11 971» | B372: Даромадҳои давраҳои оянда (ӯҳдадорӣ дар назди буҷети ҷумҳуриявӣ) | C372: 13 | D372: Поступление будущих периодов (обязательства перед республиканским бюджетом)
A373: «2 11 972» | B373: Даромадҳои давраҳои оянда (ӯҳдадорӣ дар назди буҷети маҳаллӣ) | C373: 13 | D373: Поступление будущих периодов (обязательства перед местным бюджетом)
A374: «2 11 973» | B374: Даромадҳои давраҳои оянда (ӯҳдадорӣ дар назди АСИН) | C374: 13
A375: «2 11 981» | B375: Ӯҳдадориҳое, ки аз ҳисоби маблағҳои аз фондҳои ғайрибуҷетии давлатӣ ба даст омада, пардохт мешаванд | C375: 13
A376: «2 11 982» | B376: Ӯҳдадориҳое, ки аз хисоби маблағҳои фонди суғуртаи ҳатмии тиббӣ, пардохт мешаванд | C376: 13
A377: «2 11 983» | B377: Ӯҳдадориҳои марбут ба кумакрасонии иҷтимоӣ ба аҳолӣ | C377: 13
A378: «2 11 991» | B378: Ӯҳдадориҳои марбут ба пардохти ҷуброн ва кўмакрасонӣаз ҳисоби маблағҳои БҶ | C378: 13
A379: «2 11 992» | B379: Ӯҳдадориҳои марбут бақарздиҳӣ дар доираи барномаҳои кўмаки иҷтимоӣ аз ҳисоби маблағҳои БҶ | C379: 13
A380: «2 11 999» | B380: Дигар ӯҳдадориҳои кӯтоҳмуддат | C380: 13
A381: «2 12 110» | B381: Ҳисобҳо барои пардохт | C381: 13
A382: «2 12 120» | B382: Пешпардохтҳои гирифташуда | C382: 13
A383: «2 12 190» | B383: Дигар ҳисобҳо барои пардохт | C383: 13
A384: «2 12 210» | B384: Қоғазҳои қиматнок, ба ғайр аз саҳмияҳо | C384: 14
A385: «2 12 220» | B385: Қарзҳои бонкӣ ва вомҳо | C385: 14
... A962: «5 47 600» | B962: Дигар тагйиротҳо дар ҳаҷм - ӯҳдадориҳои марбут ба иҷораи молиявӣ | C962: 11
A963: «6 10 000» | B963: Маҷмӯи даромадҳо ва хароҷот
A964: «7 10 000» | B964: Дороиҳои иҷоравӣ
A965: «7 20 000» | B965: Арзишхои молию моддии ба амонати масъулиятдор кабулшуда
A966: «7 30 000» | B966: Варақаҳои ҳисоботашон қатъӣ
A967: «7 40 000» | B967: Ҳуҷҷатҳои пулӣ
A968: «7 50 000» | B968: Қарздории соқитшудаи дебиторони қобилияти пардохт надошта
A969: «7 60 000» | B969: Қарздории хонандагон ва донишчуён оиди дороиҳои арзишноки бозгардонида нашуда
A970: «7 70 000» | B970: Ҷоизаҳо ва ҷомҳои гузарандаи варзишӣ
A971: «7 80 000» | B971: Роҳхатҳои пардохтнашуда (ройгон)
A972: «7 90 000» | B972: Ҳуҷҷатҳои ҳисоббаробаркунии мунтазири иҷроиш

Sheet ОСВ
B2: Вид счёта | D2: № | E2: Номгуй | F2: Сальдо 01.01.26 | H2: Гардиши давра | J2: Сальдо 31.01.26
F3: Дт | G3: Кт | H3: Дт | I3: Кт | J3: Дт | K3: Кт
B4: Активный счёт | D4: ='План счетов'!A2 -> «1 11 110» | E4: ='План счетов'!B2 -> Воситаҳои пулӣ бо асъори миллӣ | F4: =602566-499310 -> 103256 | H4: 143000 | I4: 25200 | J4: =F4+H4-I4 -> 221056
D5: ='План счетов'!A18 -> «1 11 254» | E5: ='План счетов'!B18 -> ҲЯХ-и ҳисобҳои шахсии маблағҳои буҷетии БМ ташкилотҳои буҷетӣ бо асъори миллӣ | F5: 122366 | H5: 201062 | J5: =F5+H5-I5 -> 323428
D6: ='План счетов'!A138 -> «1 23 100» | E6: ='План счетов'!B138 -> Ҳисобҳо барои қабул
D7: ='План счетов'!A94 -> «1 14 610» | E7: ='План счетов'!B94 -> Қарздориҳои дебитории шахсҳои ҳисобдеҳ
D8: ='План счетов'!A100 -> «1 15 100» | E8: ='План счетов'!B100 -> Пешпардохтҳои додашуда барои молхо
D9: ='План счетов'!A101 -> «1 15 200» | E9: ='План счетов'!B101 -> Пешпардохтҳои додашуда барои иљрои кор ва хизматрасониҳо
D10: ='План счетов'!A102 -> «1 15 300» | E10: ='План счетов'!B102 -> Пешпардохтҳои додашуда барои иҷора
D11: ='План счетов'!A106 -> «1 15 900» | E11: ='План счетов'!B106 -> Дигар пешпардохтҳои додашуда
D12: ='План счетов'!A155 -> «1 31 120» | E12: ='План счетов'!B155 -> Захираҳои озуқаворӣ
D13: ='План счетов'!A156 -> «1 31 210» | E13: ='План счетов'!B156 -> Молҳои канселярӣ ва асбобҳои таълимӣ
D14: ='План счетов'!A157 -> «1 31 211» | E14: ='План счетов'!B157 -> Молҳои хоҷагӣ ва инвентар
D15: ='План счетов'!A158 -> «1 31 212» | E15: ='План счетов'!B158 -> Маводҳои хароҷотӣ
D16: ='План счетов'!A159 -> «1 31 213» | E16: ='План счетов'!B159 -> Инвентари мулоим ва либоси расмӣ
D17: ='План счетов'!A160 -> «1 31 214» | E17: ='План счетов'!B160 -> Маҳсулоти хўрока
D18: ='План счетов'!A162 -> «1 31 216» | E18: ='План счетов'!B162 -> Сўзишворӣ-равғанҳои молиданӣ
D19: ='План счетов'!A163 -> «1 31 217» | E19: ='План счетов'!B163 -> Сўзишворӣ дар ҳисоботдиҳии ронандагон
D20: ='План счетов'!A164 -> «1 31 218» | E20: ='План счетов'!B164 -> Истифодабарии захираҳои молӣ-маводӣ (ЗММ)
D21: ='План счетов'!A165 -> «1 31 219» | E21: ='План счетов'!B165 -> Молҳои дигаре, ки ба дараҷаҳои дигар мансубнадошта
D22: ='План счетов'!A166 -> «1 31 220» | E22: ='План счетов'!B166 -> Истеҳсолоти нотамом
D23: ='План счетов'!A167 -> «1 31 230» | E23: ='План счетов'!B167 -> Маҳсулоти тайёр
C24: Основные средства | D24: ='План счетов'!A170 -> «1 41 110» | E24: ='План счетов'!B170 -> Биноҳои истиқоматӣ (истиқоматгоҳ)
D25: ='План счетов'!A171 -> «1 41 120» | E25: ='План счетов'!B171 -> Биноҳои ғайриистиқоматӣ | F25: 200000 | J25: =F25+H25-I25 -> 200000
D26: ='План счетов'!A172 -> «1 41 210» | E26: ='План счетов'!B172 -> Иншоот | F26: 200000 | J26: =F26+H26-I26 -> 200000
D27: ='План счетов'!A173 -> «1 41 220» | E27: ='План счетов'!B173 -> Дастгоҳҳои таҳвилдиҳӣ | F27: 25000 | J27: =F27+H27-I27 -> 25000
D28: ='План счетов'!A174 -> «1 41 310» | E28: ='План счетов'!B174 -> Таҷҳизоти нақлиётӣ | F28: 15500 | J28: =F28+H28-I28 -> 15500
D29: ='План счетов'!A175 -> «1 41 320» | E29: ='План счетов'!B175 -> Дигар мошинҳо ва таҷҳизот
D30: ='План счетов'!A176 -> «1 41 400» | E30: ='План счетов'!B176 -> Мебел, лавозимоти идора,асбобҳо, инвентари истеҳсолӣ ва хоҷагидорӣ | F30: 55000 | J30: =F30+H30-I30 -> 55000
D31: ='План счетов'!A177 -> «1 41 500» | E31: ='План счетов'!B177 -> Ободонии замин
B32: Контрактивный счёт | C32: Износ / амортизация | D32: ='План счетов'!A178 -> «1 42 110» | E32: ='План счетов'!B178 -> Фарсудашавии ҷамъшуда - биноҳои истиқоматӣ
D33: ='План счетов'!A179 -> «1 42 120» | E33: ='План счетов'!B179 -> Фарсудашавии ҷамъшуда - биноҳои ғайриистиқоматӣ | G33: 25522 | I33: 2500 | K33: =G33+I33-H33 -> 28022
D34: ='План счетов'!A180 -> «1 42 210» | E34: ='План счетов'!B180 -> Фарсудашавии ҷамъшуда - иншоот | G34: 25522 | I34: 2500 | K34: =G34+I34-H34 -> 28022
D35: ='План счетов'!A181 -> «1 42 220» | E35: ='План счетов'!B181 -> Фарсудашавии ҷамъшуда - иншоот | G35: 2500 | I35: 400 | K35: =G35+I35-H35 -> 2900
D36: ='План счетов'!A182 -> «1 42 310» | E36: ='План счетов'!B182 -> Фарсудашавии ҷамъшуда - таҷҳизоти нақлиётӣ | G36: 1500 | I36: 300 | K36: =G36+I36-H36 -> 1800
D37: ='План счетов'!A183 -> «1 42 320» | E37: ='План счетов'!B183 -> Фарсудашавии ҷамъшуда - дигар мошинҳо ва таҷҳизот
D38: ='План счетов'!A184 -> «1 42 400» | E38: ='План счетов'!B184 -> Фарсудашавии ҷамъшуда – Мебел, лавозимоти идора, асбобҳо, инвентари истеҳсолӣ ва хоҷагидорӣ | G38: 25000 | I38: 1000 | K38: =G38+I38-H38 -> 26000
D39: ='План счетов'!A185 -> «1 42 500» | E39: ='План счетов'!B185 -> Фарсудашавии ҷамъшуда - ободонии замин
B40: Активный счёт | C40: Нематериальные активы | D40: ='План счетов'!A211 -> «1 49 100» | E40: ='План счетов'!B211 -> Таъминоти барномавӣ | H40: 15000 | J40: =F40+H40-I40 -> 15000
D41: ='План счетов'!A212 -> «1 49 200» | E41: ='План счетов'!B212 -> Веб-сайтҳо
D42: ='План счетов'!A216 -> «1 49 900» | E42: ='План счетов'!B216 -> Дигар дороиҳои ғайримоддӣ
B43: Контрактивный счёт | C43: Износ / амортизация | D43: ='План счетов'!A217 -> «1 50 000» | E43: ='План счетов'!B217 -> Истеҳлоки ҷамъшудаи дороиҳои ғайримоддӣ | I43: 1500 | K43: =G43+I43-H43 -> 1500
B44: Пассивный счёт | D44: ='План счетов'!A313 -> «2 11 110» | E44: ='План счетов'!B313 -> Ҳисобҳо барои пардохт | G44: 266634 | K44: =G44+I44-H44 -> 266634
D45: ='План счетов'!A314 -> «2 11 120» | E45: ='План счетов'!B314 -> Пешпардохтҳои гирифташуда | G45: 10000 | K45: =G45+I45-H45 -> 10000
D46: ='План счетов'!A320 -> «2 11 190» | E46: ='План счетов'!B320 -> Дигар ҳисобҳо барои пардохт | G46: 364444 | K46: =G46+I46-H46 -> 364444
D47: ='План счетов'!A331 -> «2 11 510» | E47: ='План счетов'!B331 -> Музди меҳнат барои пардохт | I47: 250000 | K47: =G47+I47-H47 -> 250000
D48: ='План счетов'!A334 -> «2 11 540» | E48: ='План счетов'!B334 -> Аъзоҳаққии иттифоқи касаба барои пардохт | I48: 36000 | K48: =G48+I48-H48 -> 36000
D49: ='План счетов'!A335 -> «2 11 541» | E49: ='План счетов'!B335 -> Аъзоҳаққии иттифоқи касаба барои пардохт - ба иттифоқи касабаи ҷумҳуриявӣ | I49: 22000 | K49: =G49+I49-H49 -> 22000
D50: ='План счетов'!A336 -> «2 11 542» | E50: ='План счетов'!B336 -> Аъзоҳаққии иттифоқи касаба барои пардохт - ба иттифоқи касабаи муассиса | I50: 17662 | K50: =G50+I50-H50 -> 17662
D51: ='План счетов'!A337 -> «2 11 550» | E51: ='План счетов'!B337 -> Депонентҳо барои пардохт
D52: ='План счетов'!A338 -> «2 11 560» | E52: ='План счетов'!B338 -> Идрорпулиҳо барои пардохт
D53: ='План счетов'!A339 -> «2 11 570» | E53: ='План счетов'!B339 -> Рухсатпулиҳо барои пардохт
D54: ='План счетов'!A340 -> «2 11 580» | E54: ='План счетов'!B340 -> Уњдадорињои њисобкардашуда ба шахсони њисоботдењ
D55: ='План счетов'!A341 -> «2 11 590» | E55: ='План счетов'!B341 -> Дигар ӯҳдадориҳои ҳисобкардашуда
D56: ='План счетов'!A344 -> «2 11 610» | E56: ='План счетов'!B344 -> Андоз аз фоида барои пардохт
D57: ='План счетов'!A345 -> «2 11 620» | E57: ='План счетов'!B345 -> Андоз аз арзиши иловашуда барои пардохт
D58: ='План счетов'!A346 -> «2 11 630» | E58: ='План счетов'!B346 -> Андози аксизӣ барои пардохт
D59: ='План счетов'!A347 -> «2 11 640» | E59: ='План счетов'!B347 -> Андоз аз амволи гайриманқул барои пардохт
D60: ='План счетов'!A348 -> «2 11 650» | E60: ='План счетов'!B348 -> Андоз аз истифодабарандагони роҳҳои автомобилгард барои пардохт
D61: ='План счетов'!A349 -> «2 11 660» | E61: ='План счетов'!B349 -> Андози иҷтимоӣ аз корманд барои пардохт
D62: ='План счетов'!A350 -> «2 11 670» | E62: ='План счетов'!B350 -> Андоз аз даромади шахсони воқеӣ барои пардохт
D63: ='План счетов'!A351 -> «2 11 680» | E63: ='План счетов'!B351 -> Андози иҷтимоӣ аз корфармо барои пардохт
D64: ='План счетов'!A352 -> «2 11 681» | E64: ='План счетов'!B352 -> 1.4% шифохонагӣ-курортӣ
B65: Капитал | D65: ='План счетов'!A464 -> «3 10 310» | E65: ='План счетов'!B464 -> Саҳмияҳои оддӣ
D66: ='План счетов'!A465 -> «3 10 320» | E66: ='План счетов'!B465 -> Саҳмияҳои имтиёзнок
D67: ='План счетов'!A466 -> «3 10 330» | E67: ='План счетов'!B466 -> Сармояи барилова пардохтшуда
B68: Доходы | D68: ='План счетов'!A605 -> «4 18 310» | E68: ='План счетов'!B605 -> Ҷорӣ
D69: ='План счетов'!A637 -> «4 42 300» | E69: ='План счетов'!B637 -> Даромадҳо аз фурӯши мол ва иҷрои кори муассисаҳои ғайрибозоргонӣ
D70: ='План счетов'!A638 -> «4 42 310» | E70: ='План счетов'!B638 -> Воридот аз ташкилотҳои зертобеъ
B71: Расходы | D71: ='План счетов'!A743 -> «5 10 100» | E71: ='План счетов'!B743 -> Музди меҳнат дар шакли пулӣ
D72: ='План счетов'!A745 -> «5 10 300» | E72: ='План счетов'!B745 -> Подошпулиҳо
D73: ='План счетов'!A746 -> «5 10 400» | E73: ='План счетов'!B746 -> Ҳаққи заҳмат
D74: ='План счетов'!A748 -> «5 11 100» | E74: ='План счетов'!B748 -> Суғуртаи иҷтимоӣ
D75: ='План счетов'!A749 -> «5 11 200» | E75: ='План счетов'!B749 -> Суғуртаи тиббӣ
D76: ='План счетов'!A750 -> «5 11 900» | E76: ='План счетов'!B750 -> Дигар суғуртаи давлатӣ
D77: ='План счетов'!A796 -> «5 12 771» | E77: ='План счетов'!B796 -> Хизматрасониҳои алоқа
D78: ='План счетов'!A751 -> «5 12 100» | E78: ='План счетов'!B751 -> Истифодаи молҳо
D79: ='План счетов'!A752 -> «5 12 110» | E79: ='План счетов'!B752 -> Молҳои таҳрирӣ ва лавозимоти таълимӣ
D80: ='План счетов'!A753 -> «5 12 120» | E80: ='План счетов'!B753 -> Молҳо ва инвентари хоҷагидорӣ
D81: ='План счетов'!A754 -> «5 12 130» | E81: ='План счетов'!B754 -> Масолеҳи масрафшаванда
D82: ='План счетов'!A755 -> «5 12 140» | E82: ='План счетов'!B755 -> Ҷиҳоз ва либоси расмии дигар, инвентари мулоим
D83: ='План счетов'!A762 -> «5 12 310» | E83: ='План счетов'!B762 -> Бензин
D84: ='План счетов'!A763 -> «5 12 320» | E84: ='План счетов'!B763 -> Сухти дизелӣ (Солярка)
D85: ='План счетов'!A767 -> «5 12 390» | E85: ='План счетов'!B767 -> Дигар маводи сухт
D86: ='План счетов'!A769 -> «5 12 420» | E86: ='План счетов'!B769 -> Таълим ва таҷдиди таълими кормандон
D87: ='План счетов'!A770 -> «5 12 430» | E87: ='План счетов'!B770 -> Хароҷоти намояндагӣ
D88: ='План счетов'!A771 -> «5 12 440» | E88: ='План счетов'!B771 -> Тайёр кардани мукофотҳо, гувоҳиномаҳо, медалҳо, сиккаҳо ва хариди тӯҳфаҳо
D89: ='План счетов'!A772 -> «5 12 450» | E89: ='План счетов'!B772 -> Хароҷоти сафарҳои хизматӣ
D90: ='План счетов'!A777 -> «5 12 510» | E90: ='План счетов'!B777 -> Хароҷоти таъмири ҷорӣ -Биноҳо ва иншоот
D91: ='План счетов'!A789 -> «5 12 710» | E91: ='План счетов'!B789 -> Энергияи барқ
D92: ='План счетов'!A801 -> «5 12 820» | E92: ='План счетов'!B801 -> Хароҷоти хизматрасонии бонк
D93: ='План счетов'!A803 -> «5 13 100» | E93: ='План счетов'!B803 -> Хароҷоти истеҳлоки воситаҳои асосӣ
D94: ='План счетов'!A805 -> «5 13 300» | E94: ='План счетов'!B805 -> Хароҷоти истеҳлоки дороиҳои ғайримоддии истеҳсолнашуда
B95: Свод доходов и расходов | D95: ='План счетов'!A963 -> «6 10 000» | E95: ='План счетов'!B963 -> Маҷмӯи даромадҳо ва хароҷот
D96: итого | F96: =SUM(F5:F94) -> 617866 | G96: =SUM(G5:G94) -> 721122 | H96: =SUM(H5:H94) -> 216062 | I96: =SUM(I5:I94) -> 333862 | J96: =SUM(J5:J94) -> 833928 | K96: =SUM(K5:K94) -> 1054984
